pan3d/__init__.py
pan3d/catalogs/__init__.py
pan3d/catalogs/esgf.py
pan3d/catalogs/file.py
pan3d/catalogs/pangeo.py
pan3d/catalogs/url.py
pan3d/catalogs/xarray.py
pan3d/custom/contour.py
pan3d/explorers/__init__.py
pan3d/explorers/analytics.py
pan3d/explorers/contour.py
pan3d/explorers/globe.py
pan3d/explorers/slicer.py
pan3d/filters/globe.py
pan3d/ui/__file_select.py
pan3d/ui/__init__.py
pan3d/ui/analytics.py
pan3d/ui/catalog_search.py
pan3d/ui/collapsible.py
pan3d/ui/contour.py
pan3d/ui/control_panel.py
pan3d/ui/globe.py
pan3d/ui/layouts.py
pan3d/ui/preview.py
pan3d/ui/rendering_settings.py
pan3d/ui/slicer.py
pan3d/ui/css/__init__.py
pan3d/ui/css/base.py
pan3d/ui/css/preview.css
pan3d/ui/css/preview.py
pan3d/ui/css/vtk_view.css
pan3d/ui/css/vtk_view.py
pan3d/utils/__init__.py
pan3d/utils/anari.py
pan3d/utils/common.py
pan3d/utils/constants.py
pan3d/utils/convert.py
pan3d/utils/globe.py
pan3d/utils/presets.json
pan3d/utils/presets.py
pan3d/utils/data/continents.vtk
pan3d/utils/data/globe_textures/bathymetry.jpg
pan3d/utils/data/globe_textures/oceanmask-light.jpg
pan3d/utils/data/globe_textures/oceanmask.jpg
pan3d/utils/data/globe_textures/source.md
pan3d/utils/data/globe_textures/watermask.jpg
pan3d/viewers/__init__.py
pan3d/viewers/catalog.py
pan3d/viewers/preview.py
pan3d/widgets/__init__.py
pan3d/widgets/clip_slice_control.py
pan3d/widgets/color_by.py
pan3d/widgets/data_information.py
pan3d/widgets/data_origin.py
pan3d/widgets/error_alert.py
pan3d/widgets/pan3d_view.py
pan3d/widgets/save_dataset_dialog.py
pan3d/widgets/scalar_bar.py
pan3d/widgets/slice_control.py
pan3d/widgets/summary_toolbar.py
pan3d/widgets/time_navigation.py
pan3d/widgets/vector_property_control.py
pan3d/xarray/__init__.py
pan3d/xarray/accessor.py
pan3d/xarray/algorithm.py
pan3d/xarray/datasets.py
pan3d/xarray/errors.py
pan3d/xarray/io.py
trame/__init__.py
trame/modules/__init__.py
trame/ui/__init__.py
trame/widgets/__init__.py
trame/widgets/pan3d.py
pan3d-1.2.0.dist-info/METADATA
pan3d-1.2.0.dist-info/WHEEL
pan3d-1.2.0.dist-info/entry_points.txt
pan3d-1.2.0.dist-info/licenses/LICENSE
pan3d-1.2.0.dist-info/RECORD
