Metadata-Version: 2.4
Name: pan3d
Version: 1.2.0
Summary: Utility package for processing and visualizing 3D datasets
Author: Kitware Inc.
License: Apache Software License
License-File: LICENSE
Keywords: Application,Framework,Interactive,Python,Web
Classifier: Development Status :: 4 - Beta
Classifier: Environment :: Web Environment
Classifier: License :: OSI Approved :: Apache Software License
Classifier: Natural Language :: English
Classifier: Operating System :: OS Independent
Classifier: Programming Language :: Python :: 3 :: Only
Classifier: Topic :: Software Development :: Libraries :: Application Frameworks
Classifier: Topic :: Software Development :: Libraries :: Python Modules
Requires-Python: >=3.9
Requires-Dist: aiohttp
Requires-Dist: requests>=2.31
Requires-Dist: vtk>=9.4.2
Requires-Dist: xarray[io,parallel]>=2023.8
Provides-Extra: all
Requires-Dist: gcsfs>=2024.2; extra == 'all'
Requires-Dist: intake-esgf>=2024.1; extra == 'all'
Requires-Dist: intake-esm>=2023.11; extra == 'all'
Requires-Dist: intake-xarray>=0.7; extra == 'all'
Requires-Dist: intake==0.7.0; extra == 'all'
Requires-Dist: s3fs>=2024.2; extra == 'all'
Requires-Dist: trame-client>=3.9.1; extra == 'all'
Requires-Dist: trame-plotly>=3.1.0; extra == 'all'
Requires-Dist: trame-vtk>=2.8.15; extra == 'all'
Requires-Dist: trame-vtklocal>=0.12.2; extra == 'all'
Requires-Dist: trame-vuetify>=3.0.1; extra == 'all'
Requires-Dist: trame>=3.9; extra == 'all'
Requires-Dist: zarr<3; extra == 'all'
Provides-Extra: dev
Requires-Dist: pre-commit; extra == 'dev'
Requires-Dist: pytest>=6; extra == 'dev'
Requires-Dist: ruff; extra == 'dev'
Provides-Extra: esgf
Requires-Dist: intake-esgf>=2024.1; extra == 'esgf'
Provides-Extra: pangeo
Requires-Dist: gcsfs>=2024.2; extra == 'pangeo'
Requires-Dist: intake-esm>=2023.11; extra == 'pangeo'
Requires-Dist: intake-xarray>=0.7; extra == 'pangeo'
Requires-Dist: intake==0.7.0; extra == 'pangeo'
Requires-Dist: s3fs>=2024.2; extra == 'pangeo'
Requires-Dist: zarr<3; extra == 'pangeo'
Provides-Extra: viewer
Requires-Dist: trame-client>=3.9.1; extra == 'viewer'
Requires-Dist: trame-plotly>=3.1.0; extra == 'viewer'
Requires-Dist: trame-vtk>=2.8.15; extra == 'viewer'
Requires-Dist: trame-vtklocal>=0.12.2; extra == 'viewer'
Requires-Dist: trame-vuetify>=3.0.1; extra == 'viewer'
Requires-Dist: trame>=3.9; extra == 'viewer'
